lczerolens_lczero_bindings-0.31.2.data/headers/eigen3/signature_of_eigen3_matrix_library
lczerolens_lczero_bindings-0.31.2.data/headers/eigen3/unsupported/Eigen/MatrixFunctions
lczerolens_lczero_bindings-0.31.2.data/headers/eigen3/unsupported/Eigen/AdolcForward
lczerolens_lczero_bindings-0.31.2.data/headers/eigen3/unsupported/Eigen/AlignedVector3
lczerolens_lczero_bindings-0.31.2.data/headers/eigen3/unsupported/Eigen/OpenGLSupport
lczerolens_lczero_bindings-0.31.2.data/headers/eigen3/unsupported/Eigen/LevenbergMarquardt
lczerolens_lczero_bindings-0.31.2.data/headers/eigen3/unsupported/Eigen/AutoDiff
lczerolens_lczero_bindings-0.31.2.data/headers/eigen3/unsupported/Eigen/NumericalDiff
lczerolens_lczero_bindings-0.31.2.data/headers/eigen3/unsupported/Eigen/NonLinearOptimization
lczerolens_lczero_bindings-0.31.2.data/headers/eigen3/unsupported/Eigen/ArpackSupport
lczerolens_lczero_bindings-0.31.2.data/headers/eigen3/unsupported/Eigen/Skyline
lczerolens_lczero_bindings-0.31.2.data/headers/eigen3/unsupported/Eigen/BVH
lczerolens_lczero_bindings-0.31.2.data/headers/eigen3/unsupported/Eigen/SpecialFunctions
lczerolens_lczero_bindings-0.31.2.data/headers/eigen3/unsupported/Eigen/Splines
lczerolens_lczero_bindings-0.31.2.data/headers/eigen3/unsupported/Eigen/KroneckerProduct
lczerolens_lczero_bindings-0.31.2.data/headers/eigen3/unsupported/Eigen/IterativeSolvers
lczerolens_lczero_bindings-0.31.2.data/headers/eigen3/unsupported/Eigen/FFT
lczerolens_lczero_bindings-0.31.2.data/headers/eigen3/unsupported/Eigen/EulerAngles
lczerolens_lczero_bindings-0.31.2.data/headers/eigen3/unsupported/Eigen/SparseExtra
lczerolens_lczero_bindings-0.31.2.data/headers/eigen3/unsupported/Eigen/Polynomials
lczerolens_lczero_bindings-0.31.2.data/headers/eigen3/unsupported/Eigen/MoreVectorization
lczerolens_lczero_bindings-0.31.2.data/headers/eigen3/unsupported/Eigen/MPRealSupport
lczerolens_lczero_bindings-0.31.2.data/headers/eigen3/unsupported/Eigen/CXX11/ThreadPool
lczerolens_lczero_bindings-0.31.2.dist-info/RECORD
lczerolens_lczero_bindings-0.31.2.dist-info/WHEEL
lczerolens_lczero_bindings-0.31.2.dist-info/COPYING
lczerolens_lczero_bindings-0.31.2.dist-info/METADATA
