Metadata-Version: 2.1
Name: lczerolens-lczero-bindings
Version: 0.31.2
Summary: Leela Chess Zero Python bindings
Author: The LCZero Authors
License:                     GNU GENERAL PUBLIC LICENSE
Classifier: Programming Language :: Python :: 3
Classifier: Topic :: Games/Entertainment :: Board Games
Classifier: Topic :: Scientific/Engineering :: Artificial Intelligence
Classifier: Environment :: GPU
Project-URL: homepage, https://github.com/Xmaster6y/lczerolens-lczero-bindings
Requires-Python: >=3.7
